autodiff/__init__.py
autodiff/function.py
autodiff/optim.py
autodiff/utils.py
autodiff/variable.py
autodiff/tests/__init__.py
autodiff/tests/test_demo.py
autodiff/tests/test_function.py
autodiff/tests/test_optim.py
autodiff/tests/test_reverse_function.py
autodiff/tests/test_reverse_variable.py
autodiff/tests/test_utils.py
autodiff/tests/test_variable.py
autodiff_ADdictedtoCS-2.2.dist-info/LICENSE.txt
autodiff_ADdictedtoCS-2.2.dist-info/METADATA
autodiff_ADdictedtoCS-2.2.dist-info/WHEEL
autodiff_ADdictedtoCS-2.2.dist-info/top_level.txt
autodiff_ADdictedtoCS-2.2.dist-info/RECORD
