Metadata-Version: 2.1
Name: autodiff-ADdictedtoCS
Version: 2.2
Summary: Automatic Differentiation Package
Home-page: https://github.com/ADdictedtoCS/cs207-FinalProject
Author: DAIKI INA
Author-email: dina@hsph.harvard.edu
License: MIT
Keywords: automatic differentiation,forward mode,reverse mode,optimizer
Platform: UNKNOWN
Classifier: Programming Language :: Python :: 3
Classifier: License :: OSI Approved :: MIT License
Classifier: Operating System :: OS Independent
Requires-Python: >=3.6
Requires-Dist: numpy
Requires-Dist: matplotlib
